phk/autotask.py
phk/baidu_aip.py
phk/data_set.py
phk/data_type.py
phk/deco.py
phk/dfa.py
phk/gexitong_jifeixitong_qidian_api.py
phk/gexitong_jifeixitong_qidian_pachong.py
phk/orm_mysql.py
phk/orm_mysql_2.py
phk/phk.py
phk/phk_dfa.py
phk/phk_test.py
phk/pmysql.py
phk/req_baidu_pc.py
phk/req_base.py
phk/seo_baidu_pc.py
phk/shanjianwang_api2_caiwu.py
phk/shanjianwang_api2_taocan.py
phk/shanjianwang_api2_taocan_ali.py
phk/shanjianwang_api2_taocan_baidu.py
phk/shanjianwang_api2_taocan_tengxun.py
phk/shanjianwang_gongyinglian_api.py
phk/shuzhi_baidu_pc_rank.py
phk/tool.py
phk/webtool.py
phk/zhangte.py
phk/zhangte_get_baidu_data.py
phk/zhanqun_shezhi_xiangsi_wenzhang.py
phk-10.dist-info/LICENSE
phk-10.dist-info/METADATA
phk-10.dist-info/WHEEL
phk-10.dist-info/top_level.txt
phk-10.dist-info/RECORD
