Metadata-Version: 2.1
Name: phk
Version: 10
Summary: me
Home-page: https://www.yuque.com/jutooy/python/
Author: jutooy
Author-email: jutooy@qq.com
License: MIT
Platform: UNKNOWN
Requires: pymysql
Requires: requests
Requires: sqlalchemy
Requires: apscheduler
Requires: jieba
Requires: Crypto
